rasa_metaform
