Metadata-Version: 2.1
Name: rasa-metaform
Version: 0.2.0
Summary: Create a Rasa form from a YAML file
Home-page: https://github.com/magnetcoop/rasa-metaform
Author: Magnet S Coop.
Author-email: info@magnet.coop
Maintainer: Kamil Hryniewicz
Maintainer-email: kamil@magnet.coop
License: UNKNOWN
Project-URL: Bug Reports, https://github.com/magnetcoop/rasa-metaform/issues
Project-URL: Source, https://github.com/magnetcoop/rasa-metaform
Platform: UNKNOWN
Classifier: Programming Language :: Python
Classifier: Programming Language :: Python :: 3.6
Classifier: Programming Language :: Python :: 3.7
Classifier: License :: OSI Approved :: Apache Software License
